paramview/__init__.py
paramview/_api.py
paramview/_app.py
paramview/_cli.py
paramview/_server.py
paramview/_watch_db.py
paramview/py.typed
paramview/static/assets/index-4ZTFlpgF.css
paramview/static/assets/index-tAJMCh2R.js
paramview/static/assets/licenses.txt
paramview/static/assets/roboto-latin-400-normal-BU1SoK4h.woff
paramview/static/assets/roboto-latin-400-normal-mTIRXP6Y.woff2
paramview/static/assets/roboto-license.txt
paramview/static/favicon.svg
paramview/static/index.html
paramview-0.5.0.dist-info/LICENSE
paramview-0.5.0.dist-info/METADATA
paramview-0.5.0.dist-info/WHEEL
paramview-0.5.0.dist-info/entry_points.txt
paramview-0.5.0.dist-info/RECORD
